immutablemodel
