Metadata-Version: 1.0
Name: django-immutablemodel
Version: 0.3.1
Summary: A base class for Django to allow immutable fields on Models
Home-page: https://github.com/red56/django-immutablemodel
Author: Rob Madole, Helder Silva, Tim Diggins
Author-email: tim@red56.co.uk
License: UNKNOWN
Keywords: django model fields immutable frozen
Platform: UNKNOWN
Classifier: Development Status :: 4 - Beta
Classifier: Framework :: Django
Classifier: Intended Audience :: Developers
Classifier: License :: OSI Approved :: BSD License
Classifier: Programming Language :: Python
Classifier: Topic :: Database
